confkit/__init__.py
confkit/config.py
confkit/data_types.py
confkit/exceptions.py
confkit/py.typed
confkit/sentinels.py
confkit/watcher.py
confkit/ext/__init__.py
confkit/ext/parsers.py
confkit/ext/pydantic.py
confkit-0.12.0.dist-info/METADATA
confkit-0.12.0.dist-info/WHEEL
confkit-0.12.0.dist-info/RECORD
