Metadata-Version: 2.4
Name: confkit
Version: 0.12.0
Summary: Lightweight and Easy to use configuration manager for Python projects
Author-email: HEROgold <martijnwieringa28@gmail.com>
Requires-Python: >=3.11
Provides-Extra: msgspec
Requires-Dist: msgspec>=0.20.0; extra == 'msgspec'
Requires-Dist: pyyaml>=6.0.3; extra == 'msgspec'
Requires-Dist: tomli-w>=1.2.0; extra == 'msgspec'
Provides-Extra: pydantic
Requires-Dist: pydantic>=2.12.5; extra == 'pydantic'
